rational_linkages/AffineMetric.py
rational_linkages/CollisionAnalyser.py
rational_linkages/CollisionFreeOptimization.py
rational_linkages/DualQuaternion.py
rational_linkages/DualQuaternionAction.py
rational_linkages/ExudynAnalysis.py
rational_linkages/FactorizationProvider.py
rational_linkages/Linkage.py
rational_linkages/MiniBall.py
rational_linkages/MotionApproximation.py
rational_linkages/MotionDesigner.py
rational_linkages/MotionFactorization.py
rational_linkages/MotionInterpolation.py
rational_linkages/NormalizedLine.py
rational_linkages/NormalizedPlane.py
rational_linkages/Plotter.py
rational_linkages/PlotterMatplotlib.py
rational_linkages/PlotterPyqtgraph.py
rational_linkages/PointHomogeneous.py
rational_linkages/Quaternion.py
rational_linkages/RationalBezier.py
rational_linkages/RationalCurve.py
rational_linkages/RationalDualQuaternion.py
rational_linkages/RationalMechanism.py
rational_linkages/SingularityAnalysis.py
rational_linkages/StaticMechanism.py
rational_linkages/TransfMatrix.py
rational_linkages/__init__.py
rational_linkages/models.py
rational_linkages/utils.py
rational_linkages/utils_rust.cpython-311-x86_64-linux-musl.so
rational_linkages/utils_rust.pyi
rational_linkages/data/bennett_ark24.pkl
rational_linkages/data/collisions_free_6r.pkl
rational_linkages/data/plane_fold_6r.pkl
rational_linkages.libs/libgcc_s-2298274a.so.1
rational_linkages-2.2.3.dist-info/METADATA
rational_linkages-2.2.3.dist-info/WHEEL
rational_linkages-2.2.3.dist-info/top_level.txt
rational_linkages-2.2.3.dist-info/RECORD
rational_linkages-2.2.3.dist-info/licenses/LICENSE
