Metadata-Version: 2.4
Name: rational-linkages
Version: 2.2.3
Summary: Rational Linkages
Author-email: Daniel Huczala <daniel.huczala@uibk.ac.at>
License-Expression: GPL-3.0-or-later
Project-URL: Homepage, https://git.uibk.ac.at/geometrie-vermessung/rational-linkages
Project-URL: Documentation, http://rational-linkages.readthedocs.io/
Project-URL: Issues, https://github.com/hucik14/rational-linkages/issues
Classifier: Programming Language :: Python :: 3
Classifier: Programming Language :: Rust
Classifier: Operating System :: OS Independent
Requires-Python: >=3.10
License-File: LICENSE
Requires-Dist: biquaternion-py>=1.2.0
Requires-Dist: numpy>=1.10.0
Requires-Dist: sympy>=1.10.0
Requires-Dist: PyQt6>=6.2.0
Requires-Dist: pyqtgraph>=0.12.4
Requires-Dist: PyOpenGL>=3.0.0
Requires-Dist: matplotlib>=3.9.0; platform_system == "Windows" and platform_machine == "ARM64"
Provides-Extra: opt
Requires-Dist: ipython>=8.0.0; extra == "opt"
Requires-Dist: scipy>=1.10.0; extra == "opt"
Requires-Dist: matplotlib>=3.9.0; extra == "opt"
Requires-Dist: gmpy2>=2.2.0; (platform_system != "Windows" and platform_machine != "ARM64") and extra == "opt"
Provides-Extra: exu
Requires-Dist: exudyn>=1.9.0; extra == "exu"
Requires-Dist: numpy-stl>=3.0.0; extra == "exu"
Requires-Dist: ngsolve>=6.2.0; extra == "exu"
Provides-Extra: doc
Requires-Dist: sphinx; extra == "doc"
Requires-Dist: sphinx-rtd-theme; extra == "doc"
Requires-Dist: nbsphinx; extra == "doc"
Requires-Dist: sphinxcontrib-bibtex; extra == "doc"
Requires-Dist: toml; extra == "doc"
Requires-Dist: pandoc; extra == "doc"
Requires-Dist: sphinx-hoverxref; extra == "doc"
Requires-Dist: gitpython; extra == "doc"
Provides-Extra: dev
Requires-Dist: build; extra == "dev"
Requires-Dist: cibuildwheel; extra == "dev"
Requires-Dist: coverage; extra == "dev"
Requires-Dist: pytest; extra == "dev"
Requires-Dist: flake8; extra == "dev"
Requires-Dist: flake8-pyproject; extra == "dev"
Requires-Dist: black; extra == "dev"
Requires-Dist: isort; extra == "dev"
Requires-Dist: twine; extra == "dev"
Dynamic: license-file
